regularized_glm/__init__.py
regularized_glm/core.py
regularized_glm/stats.py
regularized_glm-1.0.2.dist-info/LICENSE
regularized_glm-1.0.2.dist-info/METADATA
regularized_glm-1.0.2.dist-info/WHEEL
regularized_glm-1.0.2.dist-info/top_level.txt
regularized_glm-1.0.2.dist-info/RECORD
