Metadata-Version: 2.1
Name: regularized-glm
Version: 1.0.2
Summary: L2-penalized generalized linear models
Home-page: https://github.com/Eden-Kramer-Lab/regularized_glm
Author: Eric Denovellis
Author-email: edeno@bu.edu
License: MIT
Platform: UNKNOWN
License-File: LICENSE
Requires-Dist: numpy (>=1.14)
Requires-Dist: statsmodels
Requires-Dist: scipy
